hito/__init__.py
hito/func/__init__.py
hito/func/engine/__init__.py
hito/func/engine/hitoFunc.py
hito/func/engine/node.py
hito/func/test/3dAlign.py
hito/func/test/__init__.py
hito/func/test/customFunc.py
hito/func/test/eccAlignFunc.py
hito/func/utils/__init__.py
hito/func/utils/func_loader.py
hito/func/utils/parameter.py
htFuncEngineTest-1.0.4.dist-info/LICENSE
htFuncEngineTest-1.0.4.dist-info/METADATA
htFuncEngineTest-1.0.4.dist-info/WHEEL
htFuncEngineTest-1.0.4.dist-info/top_level.txt
htFuncEngineTest-1.0.4.dist-info/RECORD
