Metadata-Version: 2.1
Name: htFuncEngineTest
Version: 1.0.4
Summary: 海拓算法可视化配置
Home-page: UNKNOWN
Author: wanglie
Author-email: lie_wangxy@163.com
License: MIT
Platform: UNKNOWN
Classifier: Topic :: Software Development :: Libraries :: Python Modules
Classifier: Programming Language :: Python :: 3.7
Classifier: Programming Language :: Python :: Implementation :: CPython
Requires-Dist: importlib
Requires-Dist: open3d
Requires-Dist: opencv-python
